<?xml version="1.0" encoding="UTF-8"?>
<addon id="skin.lyrebird" name="Lyrebird" version="0.6.0" provider-name="Rufoo">
    <requires>
        <import addon="xbmc.gui" version="5.14.0"/>
        <import addon="resource.images.studios.white" version="0.0.6"/>
        <import addon="script.skinshortcuts" version="0.6.6"/>
        <import addon="script.toolbox" version="1.0.0"/>
    </requires>
    <extension point="xbmc.gui.skin" debugging="false" effectslowdown="0.75">
        <res width="1920" height="1080" aspect="16:9" default="true" folder="1080i" />
    </extension>
    <extension point="xbmc.addon.metadata">
        <summary lang="en_AU">Lyrebird: For Kodi Gamers</summary>
        <summary lang="en_GB">Lyrebird: For Kodi Gamers</summary>
        <summary lang="en_NZ">Lyrebird: For Kodi Gamers</summary>
        <summary lang="en_US">Lyrebird: For Kodi Gamers</summary>
        <description lang="en_AU">Lyrebird: A blend of Mimic and the Cirrus Extended family.</description>
        <description lang="en_GB">Lyrebird: A blend of Mimic and the Cirrus Extended family.</description>
        <description lang="en_NZ">Lyrebird: A blend of Mimic and the Cirrus Extended family.</description>
        <description lang="en_US">Lyrebird: A blend of Mimic and the Cirrus Extended family.</description>
        <platform>all</platform>
        <license>CC BY-NC-SA 4.0</license>
        <forum>http://forum.kodi.tv/forumdisplay.php?fid=218</forum>
        <website></website>
        <email></email>
        <source>https://github.com/rufoo/skin.lyrebird</source>
        <assets>
            <icon>resources/icon.png</icon>
            <fanart>resources/fanart.jpg</fanart>
            <screenshot>resources/screenshot-01.jpg</screenshot>
            <screenshot>resources/screenshot-02.jpg</screenshot>
            <screenshot>resources/screenshot-03.jpg</screenshot>
            <screenshot>resources/screenshot-04.jpg</screenshot>
            <screenshot>resources/screenshot-05.jpg</screenshot>
            <screenshot>resources/screenshot-06.jpg</screenshot>
            <screenshot>resources/screenshot-07.jpg</screenshot>
            <screenshot>resources/screenshot-08.jpg</screenshot>
            <screenshot>resources/screenshot-09.jpg</screenshot>
            <screenshot>resources/screenshot-10.jpg</screenshot>
        </assets>
        <news>0.6.0 - The Arcade Begins!</news>
    </extension>
</addon>
